{
    "key": "group_655378116f7af",
    "title": "Navbar",
    "fields": [
        {
            "key": "field_655378114f11e",
            "label": "Navbar Colour",
            "name": "navbar_color",
            "aria-label": "",
            "type": "select",
            "instructions": "",
            "required": 0,
            "conditional_logic": 0,
            "wrapper": {
                "width": "",
                "class": "",
                "id": ""
            },
            "show_in_graphql": 1,
            "choices": {
                "white": "White",
                "red": "Red"
            },
            "default_value": "white",
            "return_format": "value",
            "multiple": 0,
            "allow_null": 0,
            "ui": 0,
            "ajax": 0,
            "placeholder": ""
        }
    ],
    "location": [
        [
            {
                "param": "post_type",
                "operator": "==",
                "value": "post"
            }
        ],
        [
            {
                "param": "post_type",
                "operator": "==",
                "value": "page"
            }
        ],
        [
            {
                "param": "post_type",
                "operator": "==",
                "value": "download"
            }
        ],
        [
            {
                "param": "post_type",
                "operator": "==",
                "value": "product"
            }
        ],
        [
            {
                "param": "post_type",
                "operator": "==",
                "value": "warranty"
            }
        ]
    ],
    "menu_order": 0,
    "position": "normal",
    "style": "default",
    "label_placement": "top",
    "instruction_placement": "label",
    "hide_on_screen": "",
    "active": true,
    "description": "",
    "show_in_rest": 0,
    "show_in_graphql": 0,
    "graphql_field_name": "navbar",
    "map_graphql_types_from_location_rules": 0,
    "graphql_types": "",
    "modified": 1700138371
}
